pypackpack-0.1.0.data/scripts/pypackpack.exe
pypackpack-0.1.0.data/scripts/ppp.exe
pypackpack/__init__.py
pypackpack/__main__.py
pypackpack-0.1.0.dist-info/licenses/LICENSE
pypackpack-0.1.0.dist-info/METADATA
pypackpack-0.1.0.dist-info/WHEEL
pypackpack-0.1.0.dist-info/top_level.txt
pypackpack-0.1.0.dist-info/RECORD
