Metadata-Version: 2.4
Name: pypackpack
Version: 0.1.0
Summary: PyPackPack (PPP) - A multiplatform solution to distribute python project
Author-email: thisisthepy <thisisthepy@gmail.com>
License:                                  Apache License
Project-URL: Homepage, https://github.com/thisisthepy/PyPackPack
Project-URL: Documentation, https://pypackpack.readthedocs.io
Project-URL: Repository, https://github.com/thisisthepy/PyPackPack
Project-URL: Bug Tracker, https://github.com/thisisthepy/PyPackPack/issues
Project-URL: Discussions, https://github.com/thisisthepy/PyPackPack/discussions
Project-URL: Changelog, https://github.com/thisisthepy/PyPackPack/blob/main/CHANGELOG.md
Classifier: Development Status :: 3 - Alpha
Classifier: Intended Audience :: Developers
Classifier: Intended Audience :: Science/Research
Classifier: License :: OSI Approved :: MIT License
Classifier: Operating System :: OS Independent
Classifier: Programming Language :: Python :: 3
Classifier: Programming Language :: Python :: 3.9
Classifier: Programming Language :: Python :: 3.10
Classifier: Programming Language :: Python :: 3.11
Classifier: Programming Language :: Python :: 3.12
Classifier: Programming Language :: Python :: 3.13
Classifier: Topic :: Scientific/Engineering :: Artificial Intelligence
Classifier: Topic :: Software Development :: Libraries :: Python Modules
Classifier: Topic :: Text Processing :: Linguistic
Requires-Python: >=3.9
License-File: LICENSE
Dynamic: license-file
